{
  "week": [
    [
      {
        "lesson_name": "https://meet.google.com/d vd-xzjb-qew КІТ проф. Войтович І. С.",
        "link": "15:45"
      },
      {
        "lesson_name": "https://meet.google.com/cnv -iupx-tud Техн. КД проф.  Безкоровайна О.В.",
        "link": "11:10"
      }
    ],
    [],
    [
      {
        "lesson_name": "ауд. 329 ст.в Савущик А. І.",
        "link": "12:45"
      },
      {
        "lesson_name": "ауд. 329 ст.в Савущик А. І.",
        "link": "14:15"
      }
    ],
    [],
    []
  ]
}