{
    "week": [
        [
            {
                "lesson_name": null,
                "lesson_number": 1,
                "link": null
            },
            {
                "lesson_name": null,
                "lesson_number": 2,
                "link": null
            },
            {
                "lesson_name": "дист. Системи комп'ютерних публікацій доц. Гнедко Н.М.",
                "lesson_number": 3,
                "link": "https://meet.google.com/rkb-sbis-cyt"
            },
            {
                "lesson_name": null,
                "lesson_number": 3,
                "link": null
            }
        ],
        [
            {
                "lesson_name": null,
                "lesson_number": 1,
                "link": null
            },
            {
                "lesson_name": "Іноземна мова ст.в. Данілова Н.Р.",
                "lesson_number": 2,
                "link": "https://meet.google.com/ycs-mnbh-hqo"
            }
        ],
        [
            {
                "lesson_name": null,
                "lesson_number": 1,
                "link": null
            },
            {
                "lesson_name": null,
                "lesson_number": 2,
                "link": null
            },
            {
                "lesson_name": "дистанційно Цифрова обробка фотографій та комп'ютерна анімація доц. Гнедко Н.М.",
                "lesson_number": 2,
                "link": "https://meet.google.com/rkb-sbis-cyt"
            },
            {
                "lesson_name": "дистанційно Розробка UI/UX дизайну та web- сервісів доц. Шроль Т.С.",
                "lesson_number": 3,
                "link": "https://meet.google.com/sgm-yccv-jnq"
            },
            {
                "lesson_name": "дистанційно Програмування мовою С/С ++ доц. Кіндрат П.В.",
                "lesson_number": 4,
                "link": "https://meet.google.com/peb-swwm-ony"
            },
            {
                "lesson_name": "дистанційно Поглиблене вивчення Java доц. Шроль Т.С.",
                "lesson_number": 4,
                "link": "https://meet.google.com/sgm-yccv-jnq"
            }
        ],
        [
            {
                "lesson_name": "Формальні мови, граматики й автомати проф. Сяський А.О. / в. Литвак А.М.",
                "lesson_number": 1,
                "link": "https://meet.google.com/xqf-xqkc-ean"
            },
            {
                "lesson_name": "Методика професійного навчання проф. Войтович І.С.",
                "lesson_number": 2,
                "link": "https://meet.google.com/dvd-xzjb-qew"
            },
            {
                "lesson_name": "Методика професійного навчання проф. Войтович І.С.",
                "lesson_number": 3,
                "link": "https://meet.google.com/dvd-xzjb-qew"
            }
        ],
        [
            {
                "lesson_name": null,
                "lesson_number": 1,
                "link": null
            },
            {
                "lesson_name": "Формальні мови, граматики й автомати проф. Сяський А.О. / в. Литвак А.М.",
                "lesson_number": 2,
                "link": "https://meet.google.com/xqf-xqkc-ean"
            },
            {
                "lesson_name": "дистанційно Програмування мовою С/С ++ доц. Кіндрат П.В.",
                "lesson_number": 3,
                "link": "https://meet.google.com/peb-swwm-ony"
            },
            {
                "lesson_name": "н/б Цифрова обробка фотографій та комп'ютерна анімація доц. Гнедко Н.М.",
                "lesson_number": 3,
                "link": "https://meet.google.com/rkb-sbis-cyt"
            }
        ]
    ]
}