{
  "week": [
    [],
    [
      {
        "lesson_name": "Н\\Б Загальна екологія проф. Лико С. М.",
        "link": "11:10"
      },
      {
        "lesson_name": "Н\\Б Загальна екологія проф. Лико С. М.",
        "link": "12:45"
      }
    ],
    [
      {
        "lesson_name": "кафедра Хімія з осн. геохім доц. Войтович О. П.",
        "link": "09:35"
      },
      {
        "lesson_name": "кафедра Хімія з осн. геохім доц. Войтович О. П.",
        "link": "11:10"
      },
      {
        "lesson_name": "кафедра Хімія з осн. геохім доц. Войтович О. П.",
        "link": "12:45"
      }
    ],
    [
      {
        "lesson_name": "ауд. 203 Іноземна мова",
        "link": "12:45"
      }
    ],
    [
      {
        "lesson_name": "Г7 ауд. 205 Вступ до спеціальності доц. Якута О. О. ",
        "link": "09:35"
      },
      {
        "lesson_name": "Г7 ауд. 205 Вступ до спеціальності доц. Якута О. О.",
        "link": "11:10"
      },
      {
        "lesson_name": "ауд. 419 Історія української культур  доц. Тюска В. Б.",
        "link": "12:45"
      },
      {
        "lesson_name": "ауд. 419 Історія української культур  доц. Тюска В. Б.",
        "link": "14:15"
      }
    ],
    [
      {
        "lesson_name": "Загальна екологія проф. Лико С. М.",
        "link": "09:35"
      },
      {
        "lesson_name": "Загальна екологія проф. Лико С. М.",
        "link": "11:10"
      }
    ]
  ]
}