{
    "week": [
        [
            {
                "lesson_name": null,
                "lesson_number": 1,
                "link": null
            },
            {
                "lesson_name": "Командоутворення та лідерство в управлінні проектами Шліхта Г.О.",
                "lesson_number": 2,
                "link": "https://meet.google.com/xsy-vsrs-aoy"
            },
            {
                "lesson_name": "Інноваційно-цифрові технології в галузі освіти Войтович І.С.",
                "lesson_number": 3,
                "link": "https://meet.google.com/dvd-xzjb-qew"
            },
            {
                "lesson_name": "Інноваційно-цифрові технології в галузі освіти Войтович І.С.",
                "lesson_number": 4,
                "link": "https://meet.google.com/dvd-xzjb-qew"
            }
        ],
        [
            {
                "lesson_name": null,
                "lesson_number": 1,
                "link": null
            },
            {
                "lesson_name": "Командоутворення та лідерство в управлінні проектами Шліхта Г.О.",
                "lesson_number": 2,
                "link": "https://meet.google.com/xsy-vsrs-aoy"
            },
            {
                "lesson_name": "Командоутворення та лідерство в управлінні проектами Шліхта Г.О.",
                "lesson_number": 3,
                "link": "https://meet.google.com/xsy-vsrs-aoy"
            }
        ],
        [
            {
                "lesson_name": null,
                "lesson_number": 1,
                "link": null
            },
            {
                "lesson_name": null,
                "lesson_number": 2,
                "link": null
            },
            {
                "lesson_name": "Командоутворення та лідерство в управлінні проектами Шліхта Г.О.",
                "lesson_number": 3,
                "link": "https://meet.google.com/xsy-vsrs-aoy"
            }
        ],
        [
            {
                "lesson_name": "Командоутворення та лідерство в управлінні проектами Шліхта Г.О.",
                "lesson_number": 1,
                "link": "https://meet.google.com/xsy-vsrs-aoy"
            },
            {
                "lesson_name": "Командоутворення та лідерство в управлінні проектами Шліхта Г.О.",
                "lesson_number": 2,
                "link": "https://meet.google.com/xsy-vsrs-aoy"
            },
            {
                "lesson_name": "Інноваційно-цифрові технології в галузі освіти Войтович І.С.",
                "lesson_number": 3,
                "link": "https://meet.google.com/dvd-xzjb-qew"
            },
            {
                "lesson_name": "Інноваційно-цифрові технології в галузі освіти Войтович І.С.",
                "lesson_number": 4,
                "link": "https://meet.google.com/dvd-xzjb-qew"
            }
        ],
        [
            {
                "lesson_name": null,
                "lesson_number": 1,
                "link": null
            },
            {
                "lesson_name": null,
                "lesson_number": 2,
                "link": null
            },
            {
                "lesson_name": "Інноваційно-цифрові технології в галузі освіти Войтович І.С.",
                "lesson_number": 3,
                "link": "https://meet.google.com/dvd-xzjb-qew"
            },
            {
                "lesson_name": "Інноваційно-цифрові технології в галузі освіти Войтович І.С.",
                "lesson_number": 4,
                "link": "https://meet.google.com/dvd-xzjb-qew"
            }
        ]
    ]
}