{
    "week": [
        [
            {
                "lesson_name": null,
                "lesson_number": 1,
                "link": null
            },
            {
                "lesson_name": "Вступ до спеціальності доц. Гнедко Н.М.",
                "lesson_number": 2,
                "link": null
            },
            {
                "lesson_name": "Комп'ютерна графіка та технології мультимедіа доц. Гнедко Н.М.",
                "lesson_number": 3,
                "link": null
            },
            {
                "lesson_name": "Комп'ютерна графіка та технології мультимедіа доц. Гнедко Н.М.",
                "lesson_number": 4,
                "link": null
            }
        ],
        [
            {
                "lesson_name": "Вища математика доц. Білецький В.В.",
                "lesson_number": 1,
                "link": null
            },
            {
                "lesson_name": "Комп'ютерна дискретна математика доц. Полюхович Н.В.",
                "lesson_number": 2,
                "link": null
            },
            {
                "lesson_name": "Комп'ютерна дискретна математика доц. Полюхович Н.В.",
                "lesson_number": 3,
                "link": null
            }
        ],
        [
            {
                "lesson_name": "Вища математика доц. Білецький В.В.",
                "lesson_number": 1,
                "link": null
            },
            {
                "lesson_name": "Комп'ютерна дискретна математика доц. Полюхович Н.В.",
                "lesson_number": 2,
                "link": null
            },
            {
                "lesson_name": "Українська мова доц. Шульжук Н.В.",
                "lesson_number": 3,
                "link": null
            }
        ],
        [
            {
                "lesson_name": "Вища математика доц. Білецький В.В.",
                "lesson_number": 1,
                "link": null
            },
            {
                "lesson_name": "Алгоритмізація і програмування доц. Бабич С.М.",
                "lesson_number": 2,
                "link": null
            },
            {
                "lesson_name": "Українська мова доц. Шульжук Н.В.",
                "lesson_number": 3,
                "link": null
            },
            {
                "lesson_name": "Вступ до спеціальності проф. Остапчук Н.О.",
                "lesson_number": 4,
                "link": null
            }
        ],
        [
            {
                "lesson_name": null,
                "lesson_number": 1,
                "link": null
            },
            {
                "lesson_name": "Алгоритмізація і програмування доц. Бабич С.М.",
                "lesson_number": 2,
                "link": null
            },
            {
                "lesson_name": "Інформаційно-комунікаційні технології доц. Полюхович Н.В.",
                "lesson_number": 3,
                "link": null
            },
            {
                "lesson_name": "Інформаційно-комунікаційні технології доц. Полюхович Н.В.",
                "lesson_number": 4,
                "link": null
            }
        ]
    ]
}